{
  "_meta": {
    "sources": [
      "loopback/common/models",
      "loopback/server/models",
      "../common/models",
      "./models",
      "../node_modules/loopback-component-passport/lib/models"
    ],
    "mixins": [
      "loopback/common/mixins",
      "loopback/server/mixins",
      "../common/mixins",
      "./mixins"
    ]
  },
  "User": {
    "dataSource": "db",
    "public": false
  },
  "accessToken": {
    "dataSource": "db",
    "public": true
  },
  "userCredential": {
    "dataSource": "db",
    "public": true
  },
  "userIdentity": {
    "dataSource": "db",
    "public": true
  },
  "ACL": {
    "dataSource": "db",
    "public": false
  },
  "RoleMapping": {
    "dataSource": "db",
    "public": true
  },
  "Role": {
    "dataSource": "db",
    "public": true
  },
  "AppModel": {
    "dataSource": "db",
    "public": false
  },
  "Setting": {
    "dataSource": "db",
    "public": true
  },
  "Product": {
    "dataSource": "db",
    "public": true,
    "$promise": {},
    "$resolved": true
  },
  "Category": {
    "dataSource": "db",
    "public": true,
    "$promise": {},
    "$resolved": true
  },
  "AuthProvider": {
    "dataSource": "db",
    "public": true
  },
  "user": {
    "dataSource": "db",
    "public": true
  },
  "Meta": {
    "dataSource": "db",
    "public": true
  },
  "Checkout": {
    "dataSource": "db",
    "public": true,
    "$promise": {},
    "$resolved": true
  },
  "Order": {
    "dataSource": "db",
    "public": true,
    "$promise": {},
    "$resolved": true
  },
  "Cart": {
    "dataSource": "db",
    "public": true,
    "$promise": {},
    "$resolved": true
  },
  "Address": {
    "dataSource": "db",
    "public": true
  },
  "Payment": {
    "dataSource": "db",
    "public": true,
    "$promise": {},
    "$resolved": true
  },
  "Shipment": {
    "dataSource": "db",
    "public": true,
    "$promise": {},
    "$resolved": true
  },
  "Zcategory": {
    "dataSource": "db",
    "public": true,
    "$promise": {},
    "$resolved": true
  },
  "Authcheck": {
    "dataSource": "db",
    "public": true
  },
  "creditcard": {
    "dataSource": "db",
    "public": true,
    "$promise": {},
    "$resolved": true
  },
  "Futures": {
    "dataSource": "db",
    "public": true,
    "$promise": {},
    "$resolved": true
  },
  "Metalfinish": {
    "dataSource": "db",
    "public": true
  },
  "Materialtype": {
    "dataSource": "db",
    "public": true
  },
  "Earringsize": {
    "dataSource": "db",
    "public": true
  },
  "Stonetype": {
    "dataSource": "db",
    "public": true
  },
  "Stonecolor": {
    "dataSource": "db",
    "public": true
  },
  "Necklacelength": {
    "dataSource": "db",
    "public": true
  }
}
